odoo10_addon_web_listview_range_select-10.0.1.0.0.99.dev5-py2.7-nspkg.pth
odoo/addons/web_listview_range_select/README.rst
odoo/addons/web_listview_range_select/__init__.py
odoo/addons/web_listview_range_select/__manifest__.py
odoo/addons/web_listview_range_select/i18n/web_listview_range_select.pot
odoo/addons/web_listview_range_select/static/description/icon.png
odoo/addons/web_listview_range_select/static/src/js/web_listview_range_select.js
odoo/addons/web_listview_range_select/templates/assets.xml
odoo10_addon_web_listview_range_select-10.0.1.0.0.99.dev5.dist-info/METADATA
odoo10_addon_web_listview_range_select-10.0.1.0.0.99.dev5.dist-info/RECORD
odoo10_addon_web_listview_range_select-10.0.1.0.0.99.dev5.dist-info/WHEEL
odoo10_addon_web_listview_range_select-10.0.1.0.0.99.dev5.dist-info/namespace_packages.txt
odoo10_addon_web_listview_range_select-10.0.1.0.0.99.dev5.dist-info/top_level.txt
